mycalc/calculator.py
meanjoo20230411-0.0.1.dist-info/METADATA
meanjoo20230411-0.0.1.dist-info/WHEEL
meanjoo20230411-0.0.1.dist-info/top_level.txt
meanjoo20230411-0.0.1.dist-info/RECORD
