Metadata-Version: 2.1
Name: meanjoo20230411
Version: 0.0.1
Summary: my calculator
Home-page: http://github.com/meanjoo/abc
Download-URL: http://github.com/meanjoo/abc/efgh.zip
Author: meanjoo
License: UNKNOWN
Platform: UNKNOWN
Classifier: Programming Language :: Python :: 3
